flask_auth0.py
birb_flask_auth0-0.7.dist-info/METADATA
birb_flask_auth0-0.7.dist-info/WHEEL
birb_flask_auth0-0.7.dist-info/top_level.txt
birb_flask_auth0-0.7.dist-info/RECORD
