Metadata-Version: 2.1
Name: birb-flask-auth0
Version: 0.7
Summary: UNKNOWN
Home-page: UNKNOWN
Author: UNKNOWN
Author-email: UNKNOWN
License: UNKNOWN
Platform: UNKNOWN
Requires-Dist: Flask (==1.1.2)
